pybeach/.DS_Store
pybeach/__init__.py
pybeach/beach.py
pybeach/classifiers/barrier_island_clf.joblib
pybeach/classifiers/mixed_clf.joblib
pybeach/classifiers/wave_embayed_clf.joblib
pybeach/support/__init__.py
pybeach/support/classifier_support.py
pybeach/support/data_support.py
pybeach-0.1.3.dist-info/LICENSE.md
pybeach-0.1.3.dist-info/WHEEL
pybeach-0.1.3.dist-info/METADATA
pybeach-0.1.3.dist-info/RECORD
