Metadata-Version: 2.1
Name: pybeach
Version: 0.1.3
Summary: A Python package for locating the dune toe on cross-shore beach profile transects.
License: MIT
Author: Tomas Beuzen
Requires-Python: >=3.8,<4.0
Classifier: License :: OSI Approved :: MIT License
Classifier: Programming Language :: Python :: 3
Classifier: Programming Language :: Python :: 3.8
Classifier: Programming Language :: Python :: 3.9
Requires-Dist: joblib (>=1.0.1,<2.0.0)
Requires-Dist: pandas (>=1.3.0,<2.0.0)
Requires-Dist: scikit-learn (>=0.24.2,<0.25.0)
